pozo/__init__.py
pozo/annotations.py
pozo/axes.py
pozo/drawable.py
pozo/graphs.py
pozo/traces.py
pozo/tracks.py
pozo/renderers/__init__.py
pozo/renderers/plotly.py
pozo/renderers/tree_table.py
pozo/renderers/hacks/__init__.py
pozo/themes/__init__.py
pozo/themes/mnemonic_tables.py
pozo/themes/theme_tools.py
pozo/units/__init__.py
pozo/units/units.py
pozo-0.10.0.dist-info/METADATA
pozo-0.10.0.dist-info/WHEEL
pozo-0.10.0.dist-info/top_level.txt
pozo-0.10.0.dist-info/RECORD
