Metadata-Version: 2.4
Name: pozo
Version: 0.10.0
Summary: Help visualizing well log data - Herramienta para visualizar registros de pozos
Author-email: Andrew Pikul <ajpikul@gmail.com>
Requires-Python: >=3.9
Requires-Dist: ood>=1.0.9
Requires-Dist: plotly>=5.18.0
Requires-Dist: colour>=0.1.5
Requires-Dist: pint>=0.23
Requires-Dist: pandas>=2.0.0
Requires-Dist: numpy>=1.26.0
Requires-Dist: kaleido>=0.2.1
Requires-Dist: ipywidgets
Requires-Dist: nbformat
Requires-Dist: lasio
